{
     "types": [
          "cpp",
          "C",
          "h",
          "H",
          "hpp",
          "cp",
          "cc",
          "hh",
          "cxx",
          "c++",
          "hxx",
          "h++",
          "cppm",
          "mpp",
          "h.in",
          "cxx.in",
          "hxx.in",
          "mm"
     ],
     "styles": {
          "keyword": {
               "fg": "@keyword",
               "bold": true
          },
          "keyword.control": {
               "fg": "@keyword",
               "bold": true
          },
          "keyword.modifier": {
               "fg": "@keyword",
               "italic": true
          },
          "keyword.visibility": {
               "fg": "@keyword",
               "bold": true
          },
          "keyword.cast": {
               "fg": "@keyword",
               "italic": true
          },
          "keyword.directive": {
               "fg": "@kt.preproc",
               "bold": true
          },
          "namespace": {
               "fg": "@java.package",
               "bold": true
          },
          "type": {
               "fg": "@type",
               "bold": true
          },
          "type.builtin": {
               "fg": "@keyword",
               "bold": true
          },
          "function": {
               "fg": "@func.decl",
               "bold": true
          },
          "function.call": {
               "fg": "@func.call"
          },
          "function.method": {
               "fg": "@func.decl",
               "italic": true
          },
          "function.method.call": {
               "fg": "@func.call",
               "italic": true
          },
          "function.macro": {
               "fg": "@func.call",
               "bold": true
          },
          "variable": {
               "fg": "@onSurface"
          },
          "variable.parameter": {
               "fg": "@variable",
               "italic": true
          },
          "variable.field": {
               "fg": "@field"
          },
          "variable.builtin": {
               "fg": "@keyword",
               "bold": true
          },
          "constant.builtin": {
               "fg": "@keyword",
               "bold": true
          },
          "constant.macro": {
               "fg": "@constant",
               "bold": true
          },
          "string": {
               "fg": "@string"
          },
          "string.special": {
               "fg": "@string",
               "bold": true
          },
          "string.escape": {
               "fg": "@func.decl",
               "bold": true
          },
          "number": {
               "fg": "@number"
          },
          "comment": {
               "fg": "@comment",
               "italic": true
          },
          "operator": {
               "fg": "@operator"
          },
          "punctuation.special": {
               "fg": "@operator",
               "bold": true
          },
          "punctuation.bracket": {
               "fg": "@outline"
          },
          "punctuation.delimiter": {
               "fg": "@onSurfaceVariant"
          }
     }
}